omt/__init__.py
omt/main.py
omt/common/__init__.py
omt/common/formater.py
omt/config/__init__.py
omt/config/settings.yaml
omt/core/__init__.py
omt/core/decorator.py
omt/core/resource.py
omt/lib/__init__.py
omt/lib/_omt
omt/lib/arthas-boot.jar
omt/lib/jmxterm-1.0.2-uber.jar
omt/lib/omt-completion.sh
omt/resources/__init__.py
omt/resources/arthas/__init__.py
omt/resources/arthas/arthas.py
omt/resources/completion/__init__.py
omt/resources/completion/completion.py
omt/resources/config/__init__.py
omt/resources/config/config.py
omt/resources/jmx/__init__.py
omt/resources/jmx/jmx.py
omt/resources/jmx/bean/__init__.py
omt/resources/jmx/bean/bean.py
omt/resources/kube/__init__.py
omt/resources/kube/kube.py
omt/resources/kube/kube_resource.py
omt/resources/kube/config/__init__.py
omt/resources/kube/config/config.py
omt/resources/kube/configmap/__init__.py
omt/resources/kube/configmap/configmap.py
omt/resources/kube/deployment/__init__.py
omt/resources/kube/deployment/deployment.py
omt/resources/kube/endpoint/__init__.py
omt/resources/kube/endpoint/endpoint.py
omt/resources/kube/endpoints/__init__.py
omt/resources/kube/endpoints/endpoints.py
omt/resources/kube/event/__init__.py
omt/resources/kube/event/event.py
omt/resources/kube/ingress/__init__.py
omt/resources/kube/ingress/ingress.py
omt/resources/kube/pod/__init__.py
omt/resources/kube/pod/pod.py
omt/resources/kube/pod/container/__init__.py
omt/resources/kube/pod/container/container.py
omt/resources/kube/pv/__init__.py
omt/resources/kube/pv/pv.py
omt/resources/kube/pvc/__init__.py
omt/resources/kube/pvc/pvc.py
omt/resources/kube/service/__init__.py
omt/resources/kube/service/service.py
omt/resources/rmq/__init__.py
omt/resources/rmq/rmq.py
omt/resources/rmq/binding/__init__.py
omt/resources/rmq/binding/binding.py
omt/resources/rmq/exchange/__init__.py
omt/resources/rmq/exchange/exchange.py
omt/resources/rmq/queue/__init__.py
omt/resources/rmq/queue/queue.py
omt/resources/rmq/user/__init__.py
oh_my_tools-0.1.dist-info/METADATA
oh_my_tools-0.1.dist-info/WHEEL
oh_my_tools-0.1.dist-info/entry_points.txt
oh_my_tools-0.1.dist-info/top_level.txt
oh_my_tools-0.1.dist-info/RECORD
